widget_code_input/__init__.py
widget_code_input/frontend.py
widget_code_input/utils.py
widget_code_input/static/widget.css
widget_code_input/static/widget.js
widget_code_input-4.0.17.dist-info/METADATA
widget_code_input-4.0.17.dist-info/WHEEL
widget_code_input-4.0.17.dist-info/licenses/LICENSE.txt
widget_code_input-4.0.17.dist-info/RECORD
