Metadata-Version: 2.4
Name: widget_code_input
Version: 4.0.17
Summary: A jupyter widget which allows users to implement small python functions dynamically and interactively.
Project-URL: Home, https://www.osscar.org/
Project-URL: Source, https://github.com/osscar-org/widget-code-input/
Author: The OSSCAR team
License: BSD 3-Clause License
License-File: LICENSE.txt
Keywords: anywidget,code_editor,code_input,jupyter,jupyterlab,osscar,widget
Classifier: Development Status :: 5 - Production/Stable
Classifier: Framework :: Jupyter
Classifier: Framework :: Jupyter :: JupyterLab
Classifier: Programming Language :: Python
Classifier: Programming Language :: Python :: 3.9
Classifier: Programming Language :: Python :: 3.10
Classifier: Programming Language :: Python :: 3.11
Classifier: Topic :: Scientific/Engineering
Requires-Python: >=3.9
Requires-Dist: anywidget>=0.9.1
Provides-Extra: dev
Requires-Dist: bumpver>=2023; extra == 'dev'
Requires-Dist: jupyterlab; extra == 'dev'
Requires-Dist: watchfiles; extra == 'dev'
